[
	{"id":1, "img":"img/livingroom.jpg", "title":"Livingroom"},
	{"id":2, "img":"img/diningroom.jpg", "title":"Diningroom"},
	{"id":3, "img":"img/bedroom.jpg", "title":"Bedroom"},
	{"id":4, "img":"img/homeoffice.jpg", "title":"Home office"},
	{"id":5, "img":"img/livingroom.jpg", "title":"Livingroom"},
	{"id":6, "img":"img/diningroom.jpg", "title":"Diningroom"},
	{"id":7, "img":"img/bedroom.jpg", "title":"Bedroom"},
	{"id":8, "img":"img/homeoffice.jpg", "title":"Home office"},
	{"id":9, "img":"img/livingroom.jpg", "title":"Livingroom"},
	{"id":10, "img":"img/diningroom.jpg", "title":"Diningroom"},
	{"id":11, "img":"img/bedroom.jpg", "title":"Bedroom"},
	{"id":12, "img":"img/homeoffice.jpg", "title":"Home office"},
	{"id":13, "img":"img/livingroom.jpg", "title":"Livingroom"},
	{"id":14, "img":"img/diningroom.jpg", "title":"Diningroom"},
	{"id":15, "img":"img/bedroom.jpg", "title":"Bedroom"},
	{"id":16, "img":"img/homeoffice.jpg", "title":"Home office"},
	{"id":17, "img":"img/livingroom.jpg", "title":"Livingroom"},
	{"id":18, "img":"img/diningroom.jpg", "title":"Diningroom"},
	{"id":19, "img":"img/bedroom.jpg", "title":"Bedroom"},
	{"id":20, "img":"img/homeoffice.jpg", "title":"Home office"}
]